{
  "plugins": {
    "blink.cmp": {
      "rev": "d2c4d170ad51e5116da7b19f2426f3b6e318161d",
      "src": "https://github.com/saghen/blink.cmp"
    },
    "blink.indent": {
      "rev": "15b3b25c2e76025733cc96df0144e9a9ef4d495c",
      "src": "https://github.com/saghen/blink.indent"
    },
    "blink.lib": {
      "rev": "b127d48bf8e9ac9cf41f6e0fbead317503f76558",
      "src": "https://github.com/saghen/blink.lib"
    },
    "blink.pairs": {
      "rev": "436857a5c2558c8f66a61ce4745d1342789a4881",
      "src": "https://github.com/saghen/blink.pairs"
    },
    "conform.nvim": {
      "rev": "619363c30309d29ffa631e67c8183f2a72caa373",
      "src": "https://github.com/stevearc/conform.nvim"
    },
    "gitsigns.nvim": {
      "rev": "25050e4ed39e628282831d4cbecb1850454ce915",
      "src": "https://github.com/lewis6991/gitsigns.nvim"
    },
    "lualine.nvim": {
      "rev": "221ce6b2d999187044529f49da6554a92f740a96",
      "src": "https://github.com/nvim-lualine/lualine.nvim"
    },
    "mason.nvim": {
      "rev": "bb639d4bf385a4d89f478b83af4d770be05ab7eb",
      "src": "https://github.com/mason-org/mason.nvim"
    },
    "mini.completion": {
      "rev": "04abe6fc7860858785ba63c435d76bf5b8b64b5f",
      "src": "https://github.com/nvim-mini/mini.completion"
    },
    "mini.pairs": {
      "rev": "30cf2f01c4aaa2033db67376b9924fa2442c05d6",
      "src": "https://github.com/nvim-mini/mini.pairs"
    },
    "nvim-lspconfig": {
      "rev": "6f76a3eeadc2ee235d74cd7d5319e95a261084af",
      "src": "https://github.com/neovim/nvim-lspconfig"
    },
    "nvim-treesitter": {
      "rev": "4916d6592ede8c07973490d9322f187e07dfefac",
      "src": "https://github.com/nvim-treesitter/nvim-treesitter"
    },
    "nvim-web-devicons": {
      "rev": "dfbfaa967a6f7ec50789bead7ef87e336c1fa63c",
      "src": "https://github.com/nvim-tree/nvim-web-devicons"
    },
    "vim-moonfly-colors": {
      "rev": "1c0a9994bb6bb5b43859c67924aabd061c4b7905",
      "src": "https://github.com/bluz71/vim-moonfly-colors"
    },
    "vscode.nvim": {
      "rev": "aa1102a7e15195c9cca22730b09224a7f7745ba8",
      "src": "https://github.com/mofiqul/vscode.nvim"
    }
  }
}
